px_utils/__init__.py
px_utils/cli.py
px_utils/fs.py
px_utils-1.1.2.dist-info/METADATA
px_utils-1.1.2.dist-info/WHEEL
px_utils-1.1.2.dist-info/entry_points.txt
px_utils-1.1.2.dist-info/RECORD
