Metadata-Version: 2.3
Name: px-utils
Version: 1.1.2
Summary: Build utilities python projects
Project-URL: homepage, https://github.com/pyprojectx/px-utils
Author-email: Houbie <ivo@houbrechts-it.be>
License: MIT
Keywords: build,pyprojectx
Classifier: Topic :: Software Development :: Build Tools
Classifier: Topic :: Software Development :: Libraries :: Python Modules
Requires-Python: >=3.8
